<?xml version="1.0" encoding="UTF-8"?>
<!--  -->
<plugin version="1">
  <name> frcurrents </name>
  <version> 1.16.8+4567.9b30eaf </version>
  <release> 0 </release>
  <summary> French Tidal Currents </summary>

  <api-version> 1.18 </api-version>
  <open-source> yes </open-source>
  <author> Mike Rossiter </author>
  <source> https://github.com/Rasbats/frcurrents_pi </source>
  <info-url> https://opencpn.org/OpenCPN/plugins/frcurrents.html </info-url>

  <description> Shows French Tidal Currents.
 </description>

  <target>debian-armhf</target>
  <target-version>13</target-version>
  <target-arch>armhf</target-arch>
  <tarball-url> https://dl.cloudsmith.io/public/opencpn/frcurrents-alpha/raw/names/frcurrents-1.16-debian-armhf-A32-13-tarball/versions/1.16.8+4567.9b30eaf/frcurrents-1.16.8+4567.9b30eaf_debian-armhf-13-armhf.tar.gz </tarball-url>
  <tarball-checksum> 1fd3ea31d91518ab592e0e6a18e628f529e0d6f062541fa89e8155c718ca8b96 </tarball-checksum>
</plugin>
