<?xml version="1.0" encoding="UTF-8"?>
<!--  -->
<plugin version="1">
  <name> survey </name>
  <version> 4.1.0+56.89dbcb3 </version>
  <release> 0 </release>
  <summary> Survey </summary>

  <api-version> 1.18 </api-version>
  <open-source> yes </open-source>
  <author> Pavel Kalian, Mike Rossiter </author>
  <source> https://github.com/rasbats/survey_pi </source>
  <info-url> https://opencpn.org/OpenCPN/plugins/survey.html </info-url>

  <description> Survey
 </description>

  <target>debian-armhf</target>
  <target-version>12</target-version>
  <target-arch>armhf</target-arch>
  <tarball-url> https://dl.cloudsmith.io/public/opencpn/survey-alpha/raw/names/survey-4.1-debian-armhf-A32-12-tarball/versions/4.1.0+56.89dbcb3/survey-4.1.0+56.89dbcb3_debian-armhf-12-armhf.tar.gz </tarball-url>
  <tarball-checksum> 7c94e951112e89bedf3f0d89e6ccbebc47f19b4616c119452a6f1ade15e6d8cd </tarball-checksum>
</plugin>
